catkin_tools_clangd/__init__.py
catkin_tools_clangd/verbs/__init__.py
catkin_tools_clangd/verbs/catkin_build_compile_cmd/__init__.py
catkin_tools_clangd/verbs/catkin_build_compile_cmd/build_compile_cmd.py
catkin_tools_clangd/verbs/catkin_build_compile_cmd/cli.py
catkin_tools_clangd-0.0.2.dist-info/LICENSE
catkin_tools_clangd-0.0.2.dist-info/METADATA
catkin_tools_clangd-0.0.2.dist-info/WHEEL
catkin_tools_clangd-0.0.2.dist-info/entry_points.txt
catkin_tools_clangd-0.0.2.dist-info/top_level.txt
catkin_tools_clangd-0.0.2.dist-info/RECORD
