Metadata-Version: 2.1
Name: catkin-tools-clangd
Version: 0.0.2
Summary: Catkin verb extension to generate clangd compile commands
Home-page: https://github.com/ardiya/catkin-tools-clangd
Author: Aditya Ardiya
Author-email: aditya.ardiya@gmail.com
License: UNKNOWN
Project-URL: Bug Tracker, https://github.com/ardiya/catkin-tools-clangd/issues
Platform: UNKNOWN
Classifier: Topic :: Software Development :: Build Tools
Classifier: Intended Audience :: Developers
Classifier: Programming Language :: Python :: 3
Classifier: License :: OSI Approved :: MIT License
Requires-Python: >2.7,>=3
License-File: LICENSE
